chiaswap/__init__.py
chiaswap/bech32m.py
chiaswap/main.py
chiaswap/pushtx.py
chiaswap/p2_delayed_or_preimage.clsp
chiaswap-0.1.3.dist-info/METADATA
chiaswap-0.1.3.dist-info/WHEEL
chiaswap-0.1.3.dist-info/entry_points.txt
chiaswap-0.1.3.dist-info/RECORD