Metadata-Version: 2.1
Name: chiaswap
Version: 0.1.3
Summary: Atomic swaps of Chia (XCH) and Bitcoin (BTC) via lightning.
License: MIT
Requires-Dist: chia-blockchain==1.2.11
